gemini_tel_bot/__init__.py
gemini_tel_bot/bot.py
gemini_tel_bot/cli.py
gemini_tel_bot/config.py
gemini_tel_bot/custom_types.py
gemini_tel_bot/db.py
gemini_tel_bot/gemini_utils.py
gemini_tel_bot/handlers.py
gemini_tel_bot/helpers.py
gemini_tel_bot/processing.py
gemini_tel_bot/api/__init__.py
gemini_tel_bot/api/webhook.py
gemini_tel_bot/multi_tool_agent/__init__.py
gemini_tel_bot/multi_tool_agent/agent.py
gemini_tel_bot/multi_tool_agent/prompt.py
gemini_tel_bot/multi_tool_agent/tools.py
gemini_tel_bot-0.1.1.dist-info/licenses/LICENSE
gemini_tel_bot-0.1.1.dist-info/METADATA
gemini_tel_bot-0.1.1.dist-info/WHEEL
gemini_tel_bot-0.1.1.dist-info/entry_points.txt
gemini_tel_bot-0.1.1.dist-info/top_level.txt
gemini_tel_bot-0.1.1.dist-info/RECORD
