Metadata-Version: 2.4
Name: gemini-tel-bot
Version: 0.1.1
Summary: A versatile Telegram bot built with Python that allows users to chat with Google Gemini models.
Author-email: Mohammad GhaffariFar <mohammaddevgermany@gmail.com>
Project-URL: Homepage, https://github.com/mohamadghaffari/gemini-tel-bot
Project-URL: Bug Tracker, https://github.com/mohamadghaffari/gemini-tel-bot/issues
Classifier: Development Status :: 3 - Alpha
Classifier: Intended Audience :: Developers
Classifier: Topic :: Communications :: Chat
Classifier: Topic :: Internet :: WWW/HTTP :: Dynamic Content
Classifier: Topic :: Scientific/Engineering :: Artificial Intelligence
Classifier: Topic :: Software Development :: Libraries :: Python Modules
Classifier: Framework :: AsyncIO
Classifier: Natural Language :: English
Classifier: License :: OSI Approved :: MIT License
Classifier: Programming Language :: Python :: 3
Classifier: Programming Language :: Python :: 3.11
Classifier: Programming Language :: Python :: 3.12
Classifier: Operating System :: OS Independent
Requires-Python: >=3.11
License-File: LICENSE
Requires-Dist: pytelegrambotapi
Requires-Dist: google-genai
Requires-Dist: supabase
Requires-Dist: gunicorn
Requires-Dist: google-api-core
Requires-Dist: telegramify-markdown[mermaid]
Requires-Dist: google-adk
Requires-Dist: fastapi
Requires-Dist: uvicorn[standard]
Provides-Extra: dev
Requires-Dist: python-dotenv; extra == "dev"
Requires-Dist: black; extra == "dev"
Requires-Dist: mypy; extra == "dev"
Requires-Dist: uv; extra == "dev"
Requires-Dist: pre-commit; extra == "dev"
Requires-Dist: isort; extra == "dev"
Requires-Dist: types-requests; extra == "dev"
Dynamic: license-file
